{
  "created_at": "2026-01-02T11:27:01.215201",
  "description": "Generate a modern, professional, and industrial-style landing page for a steel manufacturing company.\n\nBusiness Overview:\nThe company specializes in manufacturing high-quality steel products for construction, infrastructure, automotive, and industrial applications. They focus on strength, durability, precision engineering, and international quality standards.\n\nTarget Audience:\n- Construction companies\n- Infrastructure developers\n- Industrial manufacturers\n- B2B buyers and exporters\n\nBrand Tone:\nStrong, reliable, industrial, professional, and trustworthy.\n\nDesign Style:\n- Industrial and corporate look\n- Clean layout with bold typography\n- Metallic color palette (steel gray, dark blue, black, silver accents)\n- Strong visual hierarchy\n- Professional imagery related to steel plants, machinery, molten steel, and finished steel products\n\nLanding Page Sections:\n1. Hero Section\n   - Powerful headline highlighting strength and reliability\n   - Subheadline emphasizing quality, innovation, and scale\n   - Call-to-action button (Get a Quote / Contact Sales)\n\n2. About Us\n   - Company background\n   - Years of experience\n   - Commitment to quality and safety standards\n\n3. Products & Solutions\n   - Structural steel\n   - Steel sheets & coils\n   - Industrial steel components\n   - Custom steel fabrication\n\n4. Why Choose Us\n   - Advanced manufacturing technology\n   - ISO-certified quality standards\n   - On-time delivery\n   - Competitive pricing\n   - Skilled workforce\n\n5. Manufacturing Process\n   - Raw material sourcing\n   - Production & quality checks\n   - Finishing & logistics\n\n6. Industries We Serve\n   - Construction\n   - Infrastructure\n   - Automotive\n   - Heavy machinery\n   - Energy & power plants\n\n7. Certifications & Compliance\n   - ISO / Global quality certifications\n   - Safety and environmental compliance\n\n8. Testimonials / Client Trust Section\n   - Trusted by leading companies\n   - Long-term partnerships\n\n9. Call to Action\n   - Request quotation\n   - Contact sales team\n\n10. Footer\n    - Company address\n    - Phone & email\n    - Social links\n\nTechnical Requirements:\n- Fully responsive (desktop, tablet, mobile)\n- SEO-friendly structure\n- Clean, well-commented HTML & CSS\n- Optimized layout for fast loading\n- Accessible and professional UI\n\nOutput:\nGenerate production-ready HTML and CSS with modern styling suitable for a steel manufacturing company landing page.",
  "plan": {
    "pages": [
      {
        "name": "home",
        "purpose": "Landing page for steel manufacturing company",
        "sections": [
          "hero",
          "products & solutions",
          "why choose us",
          "manufacturing process",
          "industries we serve",
          "certifications & compliance",
          "testimonials",
          "cta"
        ]
      },
      {
        "name": "about",
        "purpose": "About the company overview",
        "sections": [
          "company background",
          "years of experience",
          "commitment to quality"
        ]
      },
      {
        "name": "contact",
        "purpose": "Contact page for inquiries",
        "sections": [
          "form",
          "company address",
          "phone and email",
          "social links"
        ]
      }
    ],
    "styling": {
      "theme": "industrial and corporate",
      "primary_color": "steel gray",
      "secondary_color": "dark blue",
      "font_family": "sans-serif",
      "design_style": "clean layout with bold typography"
    },
    "image_sections": [
      "hero",
      "products & solutions",
      "testimonials"
    ],
    "navigation": [
      "home",
      "about",
      "products & solutions",
      "contact"
    ]
  },
  "pages": [
    "home",
    "about",
    "contact"
  ],
  "image_urls": {
    "hero": "http://localhost:8000/uploads/hero_1766668485.png",
    "products & solutions": "http://localhost:8000/uploads/placeholder.png",
    "testimonials": "http://localhost:8000/uploads/testimonials_1766668479.png"
  },
  "has_global_css_theme": false
}